mlprimer/__init__.py
mlprimer/bootstrap.py
mlprimer/correlation.py
mlprimer/model_selection.py
mlprimer/preprocessing.py
mlprimer/statistics.py
mlprimer/tuning.py
mlprimer-1.0.8.dist-info/licenses/LICENSE
mlprimer-1.0.8.dist-info/METADATA
mlprimer-1.0.8.dist-info/WHEEL
mlprimer-1.0.8.dist-info/top_level.txt
mlprimer-1.0.8.dist-info/RECORD
