Metadata-Version: 2.4
Name: mlprimer
Version: 1.0.8
Summary: Complete ML pipeline for rapid model selection, tuning, and export.
Author: Emre Can Konca
License-Expression: MIT
Project-URL: Homepage, https://pypi.org/project/mlprimer/
Project-URL: Repository, https://github.com/emrec/mlprimer
Project-URL: Issues, https://github.com/emrec/mlprimer/issues
Keywords: machine-learning,ml,scikit-learn,automl,model-selection,hyperparameter-tuning
Classifier: Programming Language :: Python :: 3
Classifier: Programming Language :: Python :: 3 :: Only
Classifier: Programming Language :: Python :: 3.8
Classifier: Programming Language :: Python :: 3.9
Classifier: Programming Language :: Python :: 3.10
Classifier: Programming Language :: Python :: 3.11
Classifier: Programming Language :: Python :: 3.12
Classifier: Intended Audience :: Developers
Classifier: Intended Audience :: Science/Research
Classifier: Topic :: Scientific/Engineering :: Artificial Intelligence
Requires-Python: >=3.8
License-File: LICENSE
Requires-Dist: pandas>=1.0.0
Requires-Dist: numpy>=1.18.0
Requires-Dist: scikit-learn>=0.24.0
Requires-Dist: scipy>=1.5.0
Requires-Dist: imbalanced-learn>=0.8.0
Provides-Extra: bayesian
Requires-Dist: scikit-optimize>=0.9.0; extra == "bayesian"
Provides-Extra: advanced
Requires-Dist: xgboost>=1.0.0; extra == "advanced"
Requires-Dist: lightgbm>=3.0.0; extra == "advanced"
Requires-Dist: catboost>=1.0.0; extra == "advanced"
Provides-Extra: all
Requires-Dist: scikit-optimize>=0.9.0; extra == "all"
Requires-Dist: xgboost>=1.0.0; extra == "all"
Requires-Dist: lightgbm>=3.0.0; extra == "all"
Requires-Dist: catboost>=1.0.0; extra == "all"
Dynamic: license-file
